iterm2_colors2rgb/__init__.py
iterm2_colors2rgb/__main__.py
iterm2_colors2rgb/iterm2_colors2rgb.py
iterm2_colors2rgb-0.1.1.dist-info/LICENSE
iterm2_colors2rgb-0.1.1.dist-info/METADATA
iterm2_colors2rgb-0.1.1.dist-info/WHEEL
iterm2_colors2rgb-0.1.1.dist-info/top_level.txt
iterm2_colors2rgb-0.1.1.dist-info/RECORD
