Metadata-Version: 2.1
Name: iterm2-colors2rgb
Version: 0.1.1
Summary: Convert iTerm2 profile colors XML file to RGB
Home-page: UNKNOWN
Author: Jeremy Schulman
License: UNKNOWN
Platform: UNKNOWN
Classifier: Development Status :: 3 - Alpha
Classifier: Intended Audience :: Developers
Classifier: Topic :: Software Development :: Libraries :: Python Modules
Classifier: License :: OSI Approved :: Apache Software License
Requires-Dist: lxml
